{
  "metaData": {
    "title": "1 Mai weekend la Roșia Montană | event",
    "text": "De 1 Mai vă așteptăm la Roșia cu trasee ghidate de drumeție (centrul istoric, galeriile romane și monumentele naturii), proiecții de filme, plimbări cu mocănița și tradiționalul ... mici și bere.",
    "img": "/assets/img/events/firstMai/presentation/displayOnShareImg.jpg"
  },
  "headline": {
    "title": "1 Mai weekend la Roșia Montană",
    "videoSource": "",
    "img": "/assets/img/events/firstMai/presentation/fullWidthImg.jpg"
  },
  "sections": [
    {
      "type": "article",
      "text": "<i class='far fa-calendar-alt'></i> Program",
      "id": "schedule"
    },
    {
      "article": {         "heading": {
      "specificArticles": [
        {
          "text": "În weekendul <b>27.04 - 01.05.2018</b> organizăm tururi ghidate și alte activități în zona noastră deosebită. <br>Ne vedem <b>vineri seara - check in -</b> la Casa Petri Roșia Montană "},
{
          "link":
            {
              "text": "(vezi aici cum ajungi)",
              "textOnMouseOver": "Click aici...",
              "link": "ro/accommodation#directions"
            }
          ]
        },
        {
          "title": "Sâmbătă",
          "text": "<b><i class='far fa-clock'></i> 09:00 - 16:00 - Tur ghidat Roșia Montană</b> <br>Începem cu o vizită la galeriile romane de la Muzeul Mineritului, iar apoi vom descoperi poveștile și legendele aurarilor printr-un tur al centrul istoric (școli cu predare în diverse limbi, biserici de diferite culte sau casele aurarilor construite de diverse popoare venite aici încă din antichitate pentru a căuta aur, motiv pentru care zona a fost propusă ca sit UNESCO).",
                      }           }         ]       }     },     {       "images": [
            {
              "text": "Tur ghidat - centrul istoric Roșia Montană.",
              "thumbnail": "assets/img/accommodation/article/guides/thumbnail/ghid-rosia-montana.jpg",
              "img": "assets/img/accommodation/article/guides/img/ghid-rosia-montana.jpg"
            },
            {
              "text": "Centrul istoric.",
              "thumbnail": "assets/img/attractions/article/sicilianStreet/thumbnail/4.jpg",
              "img": "assets/img/attractions/article/sicilianStreet/img/4.jpg"
            },
            {
              "text": "Muzeul Mineritului - Galeriile Romane construite în 106 – 272 d. Hr.",
              "thumbnail": "assets/img/attractions/article/romanGalleries/thumbnail/1.jpg",
              "img": "assets/img/attractions/article/romanGalleries/img/1.jpg"
            },
            {
              "text": "Popas cu priveliște.",
              "thumbnail": "assets/img/attractions/article/panoramicBench/thumbnail/2.jpg",
              "img": "assets/img/attractions/article/panoramicBench/img/2.jpg"
            }
          ]
        },
        {
          "text": "<br><br><b><i class='far fa-clock'></i> Seara - Proiecție în grădină 'De ce e Roșia și Montană?'</b><br> Imagini, filme și povești despre trecutul și evoluția satului, modul de extracție al aurului din trecut până în prezent și viața de azi (dacă va fi frig vom ține proiecția în interior).",
                      }           }         ]       }     },     {       "images": [
            {
              "text": "Proiecții în grădină",
              "thumbnail": "assets/img/accommodation/article/outside/thumbnail/film-proiectie-gradina-casa-petri.jpg",
              "img": "assets/img/accommodation/article/outside/img/film-proiectie-gradina-casa-petri.jpg"
            },
            {
              "text": "Imagini din proiecție",
              "thumbnail": "assets/img/accommodation/article/outside/thumbnail/gardenMovieScreenShots.jpg",
              "img": "assets/img/accommodation/article/outside/img/gardenMovieScreenShots.jpg"
            }
          ]
        },
        {
          "title": "Duminică",
          "text": "<b><i class='far fa-clock'></i> 09:00 ~ 14:00 - Tur ghidat - Poveștile aurului</b> <br>Pornim pe urmele vechilor filoane de aur, vizităm galeriile masivului Cârnic și aflăm povestea și modul de realizare al acestora.",
                      }           }         ]       }     },     {       "images": [
            {
              "text": "Galeriile Cârnic",
              "thumbnail": "assets/img/attractions/article/carnic/galleries/thumbnail/1.jpg",
              "img": "assets/img/attractions/article/carnic/galleries/img/1.jpg"
            },
            {
              "text": "Piatra Corbului Cârnic - în interior sunt cele mai vechi galerii din zonă, realizate printr-o tehnică specială.",
              "thumbnail": "assets/img/attractions/article/carnic/ravenStone/thumbnail/1.jpg",
              "img": "assets/img/attractions/article/carnic/ravenStone/img/1.jpg"
            },
            {
              "text": "Galeria Văidoaia.",
              "thumbnail": "assets/img/attractions/article/vaidoaiaGalleries/thumbnail/3.jpg",
              "img": "assets/img/attractions/article/vaidoaiaGalleries/img/3.jpg"
            }
          ]
        },
        {
          "text": "<br><br><b><i class='far fa-clock'></i> Seara - Proiecție în grădină</b><br> Vom urmări filme realizate în anii '70 în Roșia Montană ca 'Nunta de piatră' (aflat în top 10 filme românești a tuturor timpurilor) sau 'Flăcări pe Comori'."
        },
        {
          "title": "Luni",
          "text": "<b><i class='far fa-clock'></i> 09:00 ~ 16:00 - Tur ghidat - masivul Detunata</b>. <br>Aici se află o arie protejată formată din coloane de bazalt de 80m înalțime la baza căruia s-a format o mare de blocuri de piatră. Aici a trait Fefeleaga (personajul lui Agârbiceanu), zona are legende impresionante, oamenii sunt primitori și alocuri se vând plăcinte cu brânză delicioase.",
                      }           }         ]       }     },     {       "images": [
            {
              "text": "<b>Detunata</b> - Printre blocurile de bazalt, în inima pădurii de molid, se formează uneori un mic ghețar.",
              "thumbnail": "assets/img/attractions/article/detunata/thumbnail/detunata3.jpg",
              "img": "assets/img/attractions/article/detunata/img/detunata3.jpg"
            },
            {
              "text": "<b>Priveliștea de pe Detunata</b> - spre ținutul Moților.",
              "thumbnail": "assets/img/attractions/article/detunata/thumbnail/lumea.jpg",
              "img": "assets/img/attractions/article/detunata/img/lumea.jpg"
            },
            {
              "text": "Pe traseu - punct de belvedere.",
              "thumbnail": "assets/img/accommodation/article/guides/thumbnail/ghid-apuseni.jpg",
              "img": "assets/img/accommodation/article/guides/img/ghid-apuseni.jpg"
            }
          ]
        },
        {
          "text": "<br><br><b><i class='far fa-clock'></i> Seara - mici, bere și vinil</b><br> Seara o vom petrece la un grătar în grădină cu mâncare tradițională de 1 Mai din partea casei (mici cu bere) și muzică de la pick-up (vinil).",
                      }           }         ]       }     },     {       "images": [
            {
              "text": "Seară cu mici și bere.",
              "thumbnail": "assets/img/events/firstMai/article/thumbnail/miciSiBere.jpg",
              "img": "assets/img/events/firstMai/article/img/miciSiBere.jpg"
            }
          ]
        },
        {
          "title": "Marți",
          "text": "<b>Plimbare cu Mocănițele din Apuseni</b> <br>Mocănițele erau folosite în trecut pentru a transporta minerii și minereul aurifer de la unzina Gura Roșia, iar acum funcționează în scop turistic. Sunt 2 mocănițe în apropiere: <b>Mocănița Abrud - Câmpeni</b> (~10min de mers cu mașina de noi; turul durează 3 ore) și <b>Mocănița Crișcior - Brad</b> (~45min de mers cu mașina de noi; turul durează 2 ore). <br><i class='fa fa-map-signs'></i> <b>Cum ajung?</b> - "},
{
          "link":
            {
              "text": "vezi harta mocănița Abrud ",
              "textOnMouseOver": "Click aici...",
              "link": "https://www.google.com/maps/dir/Casa+Petri+Rosia+Montana,+Historical+center,+nr.+331A,+Ro%C8%99ia+Montan%C4%83+517615,+Romania/Gura+Ro%C8%99iei,+Romania/Mocanita+Abrud-Campeni,+Strada+G%C4%83rii,+Abrud,+Romania/@46.2912065,23.0596886,13.22z/data=!4m20!4m19!1m5!1m1!1s0x474ecce046c99d41:0xc76f83a95070630c!2m2!1d23.129873!2d46.3065798!1m5!1m1!1s0x474ed28464e658bb:0x8b049d4bab38bf2e!2m2!1d23.0619642!2d46.307281!1m5!1m1!1s0x474ecded9cc9eb57:0x142db33519215b05!2m2!1d23.0595852!2d46.2800881!3e0?hl=en-US"
            },
            {
              "text": " | vezi harta mocănița Crișcior",
              "textOnMouseOver": "Click aici...",
              "link": "https://www.google.ro/maps/dir/Casa+Petri+Rosia+Montana,+Ro%C8%99ia+Montan%C4%83/Cri%C8%99cior/@46.2155288,22.8577319,11z/data=!3m1!4b1!4m14!4m13!1m5!1m1!1s0x474ecce046c99d41:0xc76f83a95070630c!2m2!1d23.129873!2d46.3065798!1m5!1m1!1s0x474edce95166256f:0x243ce1f1a0f481fb!2m2!1d22.866127!2d46.1234715!3e0"
            },
            {
              "text": "<br>Vezi programul mocăniței și date de contact",
              "textOnMouseOver": "Click aici...",
              "link": "http://www.cfi.ro/index.php?p=1_15"
            }
          ],
                      }           }         ]       }     },     {       "images": [
            {
              "text": "Cu mocănița prin Apuseni",
              "thumbnail": "assets/img/attractions/article/steamTrain/thumbnail/1.jpg",
              "img": "assets/img/attractions/article/steamTrain/img/1.jpg"
            },
            {
              "text": "Cu mocănița prin Apuseni",
              "thumbnail": "assets/img/attractions/article/steamTrain/thumbnail/2.jpg",
              "img": "assets/img/attractions/article/steamTrain/img/2.jpg"
            }
          ]
        }
      ]
    },
    {
      "type": "article",
      "text": "<i class='fa fa-info-circle'></i> Info",
      "id": "info"
    },
    {
      "article": {         "heading": {
      "commonArticles": {
        "category": "ourServices",
        "ids": [
          {
            "id": "eventsInfo"
          }
        ]
      }
    },
    {
      "type": "article",
      "text": "<i class='far fa-calendar-check'></i> Prețuri și Rezervări",
      "id": "bookings"
    },
    {
      "article": {         "heading": {
      "specificArticles": [
        {
          "text": "<br>Prețul este <b>450lei</b>/persoană. <b>Include</b> cazarea, traseele ghidate și proiecțiile. <b>Nu include</b> mâncarea și biletele de intrare la obiective."
        }
      ]
    },
    {
      "article": {         "heading": {
      "commonArticles": {
        "category": "ourServices",
        "ids": [
          {
            "id": "eventsBookingForm"
          },
          {
            "id": "eventsFacebookInterested"
          }
        ]
      }
    },
    {
      "type": "socialButtons"
    }
  ]
}
